neval/__init__.py
neval/_neval.py
neval/flagged_dict.py
neval/util.py
neval/version.py
neval-0.0.6.dist-info/LICENSE
neval-0.0.6.dist-info/METADATA
neval-0.0.6.dist-info/WHEEL
neval-0.0.6.dist-info/top_level.txt
neval-0.0.6.dist-info/RECORD
