Metadata-Version: 2.1
Name: neval
Version: 0.0.6
Summary: Execute raw Python code in an isolated namespace
Home-page: https://github.com/AutoActuary/neval
Author: AutoActuary
Classifier: Programming Language :: Python :: 3
Classifier: License :: Other/Proprietary License
Classifier: Operating System :: OS Independent
Requires-Python: >=3.4
License-File: LICENSE
